openwrt_ubus_client/__init__.py
openwrt_ubus_client/client.py
openwrt_ubus_client-0.1.0.dist-info/METADATA
openwrt_ubus_client-0.1.0.dist-info/WHEEL
openwrt_ubus_client-0.1.0.dist-info/licenses/LICENSE
openwrt_ubus_client-0.1.0.dist-info/RECORD
